capellambse/OpenSans-Regular.ttf
capellambse/OpenSans-Regular.ttf.license
capellambse/__init__.py
capellambse/__main__.py
capellambse/_compiled.pyi
capellambse/_diagram_cache.py
capellambse/_namespaces.py
capellambse/_native.py
capellambse/cli_helpers.py
capellambse/decl.py
capellambse/diagram_cache.py
capellambse/helpers.py
capellambse/py.typed
capellambse/repl.py
capellambse/sphinx.py
capellambse/_scripts/__init__.py
capellambse/_scripts/decl_apply.py
capellambse/_scripts/export_diagrams.py
capellambse/_scripts/filter_derive.py
capellambse/_scripts/list_known.py
capellambse/_scripts/repl.py
capellambse/_scripts/validate.py
capellambse/aird/__init__.py
capellambse/aird/_box_factories.py
capellambse/aird/_common.py
capellambse/aird/_edge_factories.py
capellambse/aird/_semantic.py
capellambse/aird/_styling.py
capellambse/aird/_visual.py
capellambse/aird/_filters/__init__.py
capellambse/aird/_filters/composite.py
capellambse/aird/_filters/global.py
capellambse/diagram/__init__.py
capellambse/diagram/_diagram.py
capellambse/diagram/_icons.py
capellambse/diagram/_json_enc.py
capellambse/diagram/_vector2d.py
capellambse/diagram/capstyle.py
capellambse/extensions/__init__.py
capellambse/extensions/filtering.py
capellambse/extensions/metrics/__init__.py
capellambse/extensions/metrics/collector.py
capellambse/extensions/metrics/composer.py
capellambse/extensions/pvmt/__init__.py
capellambse/extensions/pvmt/_config.py
capellambse/extensions/pvmt/_objects.py
capellambse/extensions/reqif/__init__.py
capellambse/extensions/reqif/_glue.py
capellambse/extensions/reqif/capellarequirements.py
capellambse/extensions/reqif/exporter.py
capellambse/extensions/reqif/requirements.py
capellambse/extensions/validation/__init__.py
capellambse/extensions/validation/__main__.py
capellambse/extensions/validation/_validate.py
capellambse/extensions/validation/report-template.html.jinja
capellambse/extensions/validation/rules.py
capellambse/filehandler/__init__.py
capellambse/filehandler/abc.py
capellambse-0.8.1.dist-info/licenses/LICENSES/Apache-2.0.txt
capellambse-0.8.1.dist-info/licenses/LICENSES/CC0-1.0.txt
capellambse-0.8.1.dist-info/licenses/LICENSES/OFL-1.1.txt
capellambse-0.8.1.dist-info/METADATA
capellambse-0.8.1.dist-info/WHEEL
capellambse-0.8.1.dist-info/entry_points.txt
capellambse-0.8.1.dist-info/top_level.txt
capellambse-0.8.1.dist-info/RECORD
