Metadata-Version: 2.4
Name: capellambse
Version: 0.8.1
Summary: Provides access to Capella MBSE projects in Python
Author: DB InfraGO AG
License-Expression: Apache-2.0 AND OFL-1.1
Project-URL: Homepage, https://github.com/dbinfrago/py-capellambse
Project-URL: Documentation, https://dbinfrago.github.io/py-capellambse
Keywords: arcadia,capella,mbse,model-based systems engineering
Platform: any
Classifier: Development Status :: 5 - Production/Stable
Classifier: Intended Audience :: Developers
Classifier: Natural Language :: English
Classifier: Operating System :: OS Independent
Classifier: Programming Language :: Python :: 3 :: Only
Classifier: Programming Language :: Python :: 3.11
Classifier: Programming Language :: Python :: 3.12
Classifier: Programming Language :: Python :: 3.13
Classifier: Programming Language :: Python :: 3.14
Classifier: Topic :: Other/Nonlisted Topic
Classifier: Topic :: Scientific/Engineering
Classifier: Topic :: Software Development :: Libraries :: Python Modules
Classifier: Typing :: Typed
Requires-Python: <3.15,>=3.11
License-File: LICENSES/Apache-2.0.txt
License-File: LICENSES/CC0-1.0.txt
License-File: LICENSES/OFL-1.1.txt
Requires-Dist: awesomeversion>=25.5.0
Requires-Dist: diskcache>=5.6.3
Requires-Dist: lxml<7,>=6.0.0
Requires-Dist: markupsafe<4.0,>=3.0.2
Requires-Dist: pillow>=12.0.0
Requires-Dist: platformdirs>=4.3.7
Requires-Dist: python-datauri>=3.0.2
Requires-Dist: pyyaml>=6.0.2
Requires-Dist: requests>=2.32.4
Requires-Dist: svgwrite>=1.4.3
Requires-Dist: typing-extensions<5,>=4.9.0
Provides-Extra: cli
Requires-Dist: click>=8.2.1; extra == "cli"
Requires-Dist: jinja2>=3.1.6; extra == "cli"
Provides-Extra: decl
Provides-Extra: httpfiles
Provides-Extra: png
Requires-Dist: cairosvg>=2.8.2; extra == "png"
Provides-Extra: termgraphics
Requires-Dist: cairosvg>=2.8.2; extra == "termgraphics"
Dynamic: license-file
